<_>
   <form_key>9LAdNoIvUtX8UQgk</form_key>
   <name>PayPal_OrderAhead</name>
   <channel>community</channel>
   <version_ids>
      <version_ids>2</version_ids>
   </version_ids>
   <summary>Complete solution for fast mobile order ahead mcommerce solution</summary>
   <description>Complete solution for fast mobile order ahead mcommerce solution
Include payment method, design package all in one</description>
   <license>Open Software License (OSL)</license>
   <license_uri>http://opensource.org/licenses/osl-3.0.php</license_uri>
   <version>0.9.1</version>
   <stability>alpha</stability>
   <notes>0.9.1: alpha release
0.9.0: first release</notes>
   <authors>
      <name>
         <name>PayPal</name>
      </name>
      <user>
         <user>PayPal</user>
      </user>
      <email>
         <email>vserpoul@paypal.com</email>
      </email>
   </authors>
   <depends_php_min>5.0.0</depends_php_min>
   <depends_php_max>5.4.0</depends_php_max>
   <depends>
      <package>
         <name>
            <name/>
         </name>
         <channel>
            <channel/>
         </channel>
         <min>
            <min/>
         </min>
         <max>
            <max/>
         </max>
         <files>
            <files>                        </files>
         </files>
      </package>
      <extension>
         <name>
            <name>Core</name>
         </name>
         <min>
            <min/>
         </min>
         <max>
            <max/>
         </max>
      </extension>
   </depends>
   <contents>
      <target>
         <target>magelocal</target>
         <target>mageetc</target>
         <target>mageetc</target>
         <target>mageetc</target>
         <target>mageetc</target>
         <target>magedesign</target>
         <target>mageskin</target>
         <target>magecommunity</target>
         <target>magecommunity</target>
         <target>magecommunity</target>
         <target>magecommunity</target>
         <target>magecommunity</target>
         <target>magedesign</target>
         <target>magedesign</target>
         <target>mageetc</target>
         <target>mageskin</target>
         <target>magecommunity</target>
         <target>mageetc</target>
         <target>magedesign</target>
         <target>magedesign</target>
         <target>mageetc</target>
         <target>magecommunity</target>
         <target>magedesign</target>
         <target>magecommunity</target>
         <target>mageetc</target>
         <target>magedesign</target>
         <target>mageetc</target>
         <target>mageetc</target>
         <target>magecommunity</target>
         <target>magecommunity</target>
         <target>magedesign</target>
         <target>magelib</target>
         <target>magedesign</target>
         <target>magecommunity</target>
         <target>magecommunity</target>
         <target>magedesign</target>
         <target>magedesign</target>
         <target>magedesign</target>
         <target>magedesign</target>
         <target>magedesign</target>
         <target>magedesign</target>
         <target>magedesign</target>
         <target>magedesign</target>
         <target>mageetc</target>
         <target>mageetc</target>
         <target>mageskin</target>
         <target>mage</target>
         <target>mage</target>
         <target>mageskin</target>
      </target>
      <path>
         <path/>
         <path>modules/Paypal_Catalog.xml</path>
         <path>modules/Paypal_Checkout.xml</path>
         <path>modules/Paypal_Core.xml</path>
         <path>modules/Paypal_Sales.xml</path>
         <path>frontend/paypal</path>
         <path>frontend/paypal</path>
         <path>Paypal/Core</path>
         <path>Paypal/Checkout</path>
         <path>Paypal/Sales</path>
         <path>Paypal/Catalog</path>
         <path>Paypal/Checkin</path>
         <path>frontend/base/default/layout/paypal/checkin.xml</path>
         <path>frontend/base/default/template/paypal/checkin</path>
         <path>modules/Paypal_Checkin.xml</path>
         <path>frontend/base/default/js/paypal/checkin</path>
         <path>Paypal/Favorite</path>
         <path>modules/Paypal_Favorite.xml</path>
         <path>frontend/base/default/template/paypal/favorite</path>
         <path>frontend/base/default/layout/paypal/favorite.xml</path>
         <path>modules/Paypal_Featuredcategory.xml</path>
         <path>Paypal/Featuredcategory</path>
         <path>frontend/base/default/layout/paypal/featuredcategory.xml</path>
         <path>Paypal/Locationhere</path>
         <path>modules/Paypal_Locationhere.xml</path>
         <path>frontend/base/default/layout/paypal/locationhere.xml</path>
         <path>modules/Paypal_Qrcode.xml</path>
         <path>modules/Paypal_Qrcodeorder.xml</path>
         <path>Paypal/Qrcode</path>
         <path>Paypal/Qrcodeorder</path>
         <path>frontend/base/default/template/paypal/qrcodeorder</path>
         <path>phpqrcode</path>
         <path>frontend/base/default/layout/paypal/qrcodeorder.xml</path>
         <path>Paypal/Pickup</path>
         <path>Paypal/Instorepickupadmin</path>
         <path>adminhtml/default/default/layout/paypal/instore_pickup_admin.xml</path>
         <path>adminhtml/default/default/layout/paypal/pickup.xml</path>
         <path>adminhtml/default/default/template/paypal/instorepickupadmin</path>
         <path>adminhtml/default/default/template/paypal/pickup</path>
         <path>frontend/base/default/layout/paypal/instore_pickup_admin.xml</path>
         <path>frontend/base/default/layout/paypal/pickup.xml</path>
         <path>frontend/base/default/template/paypal/instorepickupadmin</path>
         <path>frontend/base/default/template/paypal/pickup</path>
         <path>modules/Paypal_Instorepickupadmin.xml</path>
         <path>modules/Paypal_Pickup.xml</path>
         <path>frontend/base/default/paypal/pickup</path>
         <path>js/paypal/instorepickup</path>
         <path>js/paypal/pickup</path>
         <path>adminhtml/default/default/paypal/pickup.css</path>
      </path>
      <type>
         <type>file</type>
         <type>file</type>
         <type>file</type>
         <type>file</type>
         <type>file</type>
         <type>dir</type>
         <type>dir</type>
         <type>dir</type>
         <type>dir</type>
         <type>dir</type>
         <type>dir</type>
         <type>dir</type>
         <type>file</type>
         <type>dir</type>
         <type>file</type>
         <type>dir</type>
         <type>dir</type>
         <type>file</type>
         <type>dir</type>
         <type>file</type>
         <type>file</type>
         <type>dir</type>
         <type>file</type>
         <type>dir</type>
         <type>file</type>
         <type>file</type>
         <type>file</type>
         <type>file</type>
         <type>dir</type>
         <type>dir</type>
         <type>dir</type>
         <type>dir</type>
         <type>file</type>
         <type>dir</type>
         <type>dir</type>
         <type>file</type>
         <type>file</type>
         <type>dir</type>
         <type>dir</type>
         <type>file</type>
         <type>file</type>
         <type>dir</type>
         <type>dir</type>
         <type>file</type>
         <type>file</type>
         <type>dir</type>
         <type>dir</type>
         <type>dir</type>
         <type>file</type>
      </type>
      <include>
         <include/>
         <include/>
         <include/>
         <include/>
         <include/>
         <include/>
         <include/>
         <include/>
         <include/>
         <include/>
         <include/>
         <include/>
         <include/>
         <include/>
         <include/>
         <include/>
         <include/>
         <include/>
         <include/>
         <include/>
         <include/>
         <include/>
         <include/>
         <include/>
         <include/>
         <include/>
         <include/>
         <include/>
         <include/>
         <include/>
         <include/>
         <include/>
         <include/>
         <include/>
         <include/>
         <include/>
         <include/>
         <include/>
         <include/>
         <include/>
         <include/>
         <include/>
         <include/>
         <include/>
         <include/>
         <include/>
         <include/>
         <include/>
         <include/>
      </include>
      <ignore>
         <ignore/>
         <ignore/>
         <ignore/>
         <ignore/>
         <ignore/>
         <ignore/>
         <ignore/>
         <ignore/>
         <ignore/>
         <ignore/>
         <ignore/>
         <ignore/>
         <ignore/>
         <ignore/>
         <ignore/>
         <ignore/>
         <ignore/>
         <ignore/>
         <ignore/>
         <ignore/>
         <ignore/>
         <ignore/>
         <ignore/>
         <ignore/>
         <ignore/>
         <ignore/>
         <ignore/>
         <ignore/>
         <ignore/>
         <ignore/>
         <ignore/>
         <ignore/>
         <ignore/>
         <ignore/>
         <ignore/>
         <ignore/>
         <ignore/>
         <ignore/>
         <ignore/>
         <ignore/>
         <ignore/>
         <ignore/>
         <ignore/>
         <ignore/>
         <ignore/>
         <ignore/>
         <ignore/>
         <ignore/>
         <ignore/>
      </ignore>
   </contents>
</_>
